court_listener/__init__.py
court_listener/apis/PACER_data.py
court_listener/apis/RECAP.py
court_listener/apis/__init__.py
court_listener/apis/alert.py
court_listener/apis/case_law.py
court_listener/apis/citation_lookup.py
court_listener/apis/citation_network.py
court_listener/apis/financial_disclosure.py
court_listener/apis/judge.py
court_listener/apis/oral_argument.py
court_listener/apis/search.py
court_listener/apis/visualization.py
court_listener/base.py
court_listener/error_handling.py
court_listener-0.0.1.dist-info/LICENSE
court_listener-0.0.1.dist-info/METADATA
court_listener-0.0.1.dist-info/WHEEL
court_listener-0.0.1.dist-info/RECORD
