Metadata-Version: 2.1
Name: court-listener
Version: 0.0.1
Summary: A python client for the Court Listener API
Home-page: https://github.com/SpyderRex/court-listener
License: MIT
Keywords: API,requests,client,courts,legal,law
Author: Spyder Rex
Author-email: billyjohnsonauthor@gmail.com
Requires-Python: >=3.8,<4.0
Classifier: License :: OSI Approved :: MIT License
Classifier: Operating System :: OS Independent
Classifier: Programming Language :: Python :: 3
Classifier: Programming Language :: Python :: 3.8
Classifier: Programming Language :: Python :: 3.9
Classifier: Programming Language :: Python :: 3.10
Classifier: Programming Language :: Python :: 3.11
Classifier: Programming Language :: Python :: 3.12
Requires-Dist: requests (>=2.26.0,<3.0.0)
Project-URL: Repository, https://github.com/SpyderRex/court-listener
